{
  "num_points": 11,
  "step_size": 0.01,
  "points": [
    {
      "index": 0,
      "position": [
        0.2626747808456422,
        -0.14904119777679445,
        1.3230487785339367
      ],
      "label": 0,
      "class_name": "Crook",
      "timestamp": "2025-11-30T18:38:58.110076"
    },
    {
      "index": 1,
      "position": [
        0.28667478084564224,
        -0.27904119777679454,
        0.8260487785339362
      ],
      "label": 0,
      "class_name": "Crook",
      "timestamp": "2025-11-30T18:40:31.008738"
    },
    {
      "index": 2,
      "position": [
        -0.280325219154358,
        -0.2470411977767945,
        0.5200487785339358
      ],
      "label": 0,
      "class_name": "Crook",
      "timestamp": "2025-11-30T18:47:34.946867"
    },
    {
      "index": 3,
      "position": [
        0.03067478084564214,
        0.014958802223205583,
        0.748048778533936
      ],
      "label": 1,
      "class_name": "Canker",
      "timestamp": "2025-11-30T18:49:03.598468"
    },
    {
      "index": 4,
      "position": [
        0.18867478084564218,
        -0.17004119777679444,
        0.8040487785339361
      ],
      "label": 1,
      "class_name": "Canker",
      "timestamp": "2025-11-30T18:50:23.836005"
    },
    {
      "index": 5,
      "position": [
        0.01867478084564215,
        -0.020041197776794424,
        0.2510487785339356
      ],
      "label": 1,
      "class_name": "Canker",
      "timestamp": "2025-11-30T18:51:30.152161"
    },
    {
      "index": 6,
      "position": [
        0.18767478084564218,
        -0.08804119777679441,
        1.242048778533937
      ],
      "label": 1,
      "class_name": "Canker",
      "timestamp": "2025-11-30T18:53:38.150742"
    },
    {
      "index": 7,
      "position": [
        -0.21332521915435787,
        -0.14904119777679442,
        0.49804877853393625
      ],
      "label": 1,
      "class_name": "Canker",
      "timestamp": "2025-11-30T18:57:28.915488"
    },
    {
      "index": 8,
      "position": [
        -0.012325219154357824,
        0.0069588022232055765,
        0.5290487785339363
      ],
      "label": 1,
      "class_name": "Canker",
      "timestamp": "2025-11-30T18:59:08.161221"
    },
    {
      "index": 9,
      "position": [
        -0.2703252191543579,
        0.1929588022232056,
        0.8050487785339365
      ],
      "label": 1,
      "class_name": "Canker",
      "timestamp": "2025-11-30T19:01:26.055006"
    },
    {
      "index": 10,
      "position": [
        -0.375325219154358,
        0.20495880222320562,
        0.8650487785339366
      ],
      "label": 0,
      "class_name": "Crook",
      "timestamp": "2025-11-30T19:02:02.268399"
    }
  ]
}